namesilo/__init__.py
namesilo/core.py
namesilo/exceptions.py
namesilo/common/__init__.py
namesilo/common/models.py
python_namesilo-1.7.0.dist-info/LICENSE
python_namesilo-1.7.0.dist-info/METADATA
python_namesilo-1.7.0.dist-info/WHEEL
python_namesilo-1.7.0.dist-info/top_level.txt
python_namesilo-1.7.0.dist-info/RECORD
