Metadata-Version: 2.1
Name: python-namesilo
Version: 1.7.0
Summary: API wrapper for Namesilo service
Home-page: https://github.com/goranvrbaski/python-namesilo
Author: Goran Vrbaski
Author-email: vrbaski.goran@gmail.com
License: GPLv3+
Classifier: Development Status :: 5 - Production/Stable
Classifier: License :: OSI Approved :: GNU General Public License v3 or later (GPLv3+)
Classifier: Operating System :: OS Independent
Classifier: Programming Language :: Python :: 3
Classifier: Programming Language :: Python :: 3.8
Classifier: Programming Language :: Python :: 3.9
Classifier: Programming Language :: Python :: 3.10
Classifier: Programming Language :: Python :: 3.11
Classifier: Programming Language :: Python :: 3.12
Classifier: Topic :: Internet :: WWW/HTTP
Classifier: Topic :: Software Development :: Libraries :: Python Modules
Requires-Python: >=3.8,<=3.12
License-File: LICENSE
Requires-Dist: requests
Requires-Dist: xmltodict
